{
    "asset": {
        "format": "jpg",
        "id": "03f7dab48b3dbffa898bc84564c487f6",
        "name": "TakeScissor_18_3.jpg",
        "path": "file:D:/Dataset/All%20data/TakeScissor_18_3.jpg",
        "size": {
            "width": 1920,
            "height": 1080
        },
        "state": 2,
        "type": 1
    },
    "regions": [
        {
            "id": "jsKEkzDv1",
            "type": "RECTANGLE",
            "tags": [
                "Tweezers"
            ],
            "boundingBox": {
                "height": 14.474226804123711,
                "width": 67.93503480278422,
                "left": 1039.6287703016242,
                "top": 545.9845360824743
            },
            "points": [
                {
                    "x": 1039.6287703016242,
                    "y": 545.9845360824743
                },
                {
                    "x": 1107.5638051044084,
                    "y": 545.9845360824743
                },
                {
                    "x": 1107.5638051044084,
                    "y": 560.4587628865979
                },
                {
                    "x": 1039.6287703016242,
                    "y": 560.4587628865979
                }
            ]
        },
        {
            "id": "nIU_mbZtGR",
            "type": "RECTANGLE",
            "tags": [
                "Tweezers"
            ],
            "boundingBox": {
                "height": 14.474226804123711,
                "width": 54.5707656612529,
                "left": 1041.8561484918794,
                "top": 564.9123711340206
            },
            "points": [
                {
                    "x": 1041.8561484918794,
                    "y": 564.9123711340206
                },
                {
                    "x": 1096.4269141531322,
                    "y": 564.9123711340206
                },
                {
                    "x": 1096.4269141531322,
                    "y": 579.3865979381444
                },
                {
                    "x": 1041.8561484918794,
                    "y": 579.3865979381444
                }
            ]
        },
        {
            "id": "MZp7wnfE0R",
            "type": "RECTANGLE",
            "tags": [
                "Scissors"
            ],
            "boundingBox": {
                "height": 18.927835051546392,
                "width": 91.32250580046403,
                "left": 1011.7865429234338,
                "top": 598.3144329896908
            },
            "points": [
                {
                    "x": 1011.7865429234338,
                    "y": 598.3144329896908
                },
                {
                    "x": 1103.1090487238978,
                    "y": 598.3144329896908
                },
                {
                    "x": 1103.1090487238978,
                    "y": 617.2422680412371
                },
                {
                    "x": 1011.7865429234338,
                    "y": 617.2422680412371
                }
            ]
        },
        {
            "id": "U8N0fcGtxX",
            "type": "RECTANGLE",
            "tags": [
                "Scissors"
            ],
            "boundingBox": {
                "height": 51.21649484536083,
                "width": 47.88863109048724,
                "left": 1129.8375870069606,
                "top": 598.3144329896908
            },
            "points": [
                {
                    "x": 1129.8375870069606,
                    "y": 598.3144329896908
                },
                {
                    "x": 1177.7262180974478,
                    "y": 598.3144329896908
                },
                {
                    "x": 1177.7262180974478,
                    "y": 649.5309278350516
                },
                {
                    "x": 1129.8375870069606,
                    "y": 649.5309278350516
                }
            ]
        },
        {
            "id": "6w-UtR4DGT",
            "type": "RECTANGLE",
            "tags": [
                "Syringe"
            ],
            "boundingBox": {
                "height": 57.896907216494846,
                "width": 17.819025522041763,
                "left": 1124.2691415313225,
                "top": 529.2835051546392
            },
            "points": [
                {
                    "x": 1124.2691415313225,
                    "y": 529.2835051546392
                },
                {
                    "x": 1142.0881670533643,
                    "y": 529.2835051546392
                },
                {
                    "x": 1142.0881670533643,
                    "y": 587.180412371134
                },
                {
                    "x": 1124.2691415313225,
                    "y": 587.180412371134
                }
            ]
        },
        {
            "id": "CaLRnUlauN",
            "type": "RECTANGLE",
            "tags": [
                "Syringe"
            ],
            "boundingBox": {
                "height": 57.896907216494846,
                "width": 25.614849187935032,
                "left": 1205.568445475638,
                "top": 653.9845360824743
            },
            "points": [
                {
                    "x": 1205.568445475638,
                    "y": 653.9845360824743
                },
                {
                    "x": 1231.183294663573,
                    "y": 653.9845360824743
                },
                {
                    "x": 1231.183294663573,
                    "y": 711.8814432989691
                },
                {
                    "x": 1205.568445475638,
                    "y": 711.8814432989691
                }
            ]
        },
        {
            "id": "lNf3H4pLEa",
            "type": "RECTANGLE",
            "tags": [
                "Syringe"
            ],
            "boundingBox": {
                "height": 74.5979381443299,
                "width": 26.728538283062644,
                "left": 1267.9350348027842,
                "top": 667.3453608247423
            },
            "points": [
                {
                    "x": 1267.9350348027842,
                    "y": 667.3453608247423
                },
                {
                    "x": 1294.6635730858468,
                    "y": 667.3453608247423
                },
                {
                    "x": 1294.6635730858468,
                    "y": 741.9432989690722
                },
                {
                    "x": 1267.9350348027842,
                    "y": 741.9432989690722
                }
            ]
        },
        {
            "id": "b_qlEnxtoB",
            "type": "RECTANGLE",
            "tags": [
                "Scissors"
            ],
            "boundingBox": {
                "height": 40.08247422680412,
                "width": 125.84686774941994,
                "left": 1010.6728538283062,
                "top": 724.1288659793814
            },
            "points": [
                {
                    "x": 1010.6728538283062,
                    "y": 724.1288659793814
                },
                {
                    "x": 1136.5197215777262,
                    "y": 724.1288659793814
                },
                {
                    "x": 1136.5197215777262,
                    "y": 764.2113402061856
                },
                {
                    "x": 1010.6728538283062,
                    "y": 764.2113402061856
                }
            ]
        },
        {
            "id": "vaAVnjV0bl",
            "type": "RECTANGLE",
            "tags": [
                "Scissors"
            ],
            "boundingBox": {
                "height": 61.23711340206186,
                "width": 100.23201856148492,
                "left": 1011.7865429234338,
                "top": 667.3453608247423
            },
            "points": [
                {
                    "x": 1011.7865429234338,
                    "y": 667.3453608247423
                },
                {
                    "x": 1112.0185614849188,
                    "y": 667.3453608247423
                },
                {
                    "x": 1112.0185614849188,
                    "y": 728.5824742268042
                },
                {
                    "x": 1011.7865429234338,
                    "y": 728.5824742268042
                }
            ]
        },
        {
            "id": "-whQ_nUMaY",
            "type": "RECTANGLE",
            "tags": [
                "Scissors"
            ],
            "boundingBox": {
                "height": 37.855670103092784,
                "width": 76.84454756380511,
                "left": 1017.3549883990719,
                "top": 635.0567010309279
            },
            "points": [
                {
                    "x": 1017.3549883990719,
                    "y": 635.0567010309279
                },
                {
                    "x": 1094.199535962877,
                    "y": 635.0567010309279
                },
                {
                    "x": 1094.199535962877,
                    "y": 672.9123711340206
                },
                {
                    "x": 1017.3549883990719,
                    "y": 672.9123711340206
                }
            ]
        },
        {
            "id": "1RyTWV_uS1",
            "type": "RECTANGLE",
            "tags": [
                "Scissors"
            ],
            "boundingBox": {
                "height": 92.63778681643748,
                "width": 84.7618431707756,
                "left": 1170.4368856284866,
                "top": 788.2325091238482
            },
            "points": [
                {
                    "x": 1170.4368856284866,
                    "y": 788.2325091238482
                },
                {
                    "x": 1255.1987287992622,
                    "y": 788.2325091238482
                },
                {
                    "x": 1255.1987287992622,
                    "y": 880.8702959402857
                },
                {
                    "x": 1170.4368856284866,
                    "y": 880.8702959402857
                }
            ]
        },
        {
            "id": "K6B4BSffH",
            "type": "RECTANGLE",
            "tags": [
                "Scissors"
            ],
            "boundingBox": {
                "height": 21.464846873001278,
                "width": 97.19354530322117,
                "left": 1014.4751481802232,
                "top": 580.3625661998196
            },
            "points": [
                {
                    "x": 1014.4751481802232,
                    "y": 580.3625661998196
                },
                {
                    "x": 1111.6686934834443,
                    "y": 580.3625661998196
                },
                {
                    "x": 1111.6686934834443,
                    "y": 601.8274130728208
                },
                {
                    "x": 1014.4751481802232,
                    "y": 601.8274130728208
                }
            ]
        },
        {
            "id": "R4EzZiFN_",
            "type": "RECTANGLE",
            "tags": [
                "Hand"
            ],
            "boundingBox": {
                "height": 73.43236422439638,
                "width": 93.80305807989923,
                "left": 947.7959035338312,
                "top": 517.0977588015545
            },
            "points": [
                {
                    "x": 947.7959035338312,
                    "y": 517.0977588015545
                },
                {
                    "x": 1041.5989616137304,
                    "y": 517.0977588015545
                },
                {
                    "x": 1041.5989616137304,
                    "y": 590.5301230259508
                },
                {
                    "x": 947.7959035338312,
                    "y": 590.5301230259508
                }
            ]
        },
        {
            "id": "l4gpWiAp1",
            "type": "RECTANGLE",
            "tags": [
                "Hand"
            ],
            "boundingBox": {
                "height": 62.13503201700911,
                "width": 82.50151835522765,
                "left": 849.472195822836,
                "top": 550.9896289421645
            },
            "points": [
                {
                    "x": 849.472195822836,
                    "y": 550.9896289421645
                },
                {
                    "x": 931.9737141780637,
                    "y": 550.9896289421645
                },
                {
                    "x": 931.9737141780637,
                    "y": 613.1246609591736
                },
                {
                    "x": 849.472195822836,
                    "y": 613.1246609591736
                }
            ]
        }
    ],
    "version": "2.1.0"
}