{
    "asset": {
        "format": "jpg",
        "id": "22a0675f65a7c53383c88bfa37d16921",
        "name": "ReturnScissor_37_10.jpg",
        "path": "file:D:/Dataset/All%20data/ReturnScissor_37_10.jpg",
        "size": {
            "width": 1920,
            "height": 1080
        },
        "state": 2,
        "type": 1
    },
    "regions": [
        {
            "id": "j-fksuLPs",
            "type": "RECTANGLE",
            "tags": [
                "Scissors"
            ],
            "boundingBox": {
                "height": 60.19359202438864,
                "width": 121.53586884154461,
                "left": 1287.155320683533,
                "top": 761.756007124053
            },
            "points": [
                {
                    "x": 1287.155320683533,
                    "y": 761.756007124053
                },
                {
                    "x": 1408.6911895250778,
                    "y": 761.756007124053
                },
                {
                    "x": 1408.6911895250778,
                    "y": 821.9495991484416
                },
                {
                    "x": 1287.155320683533,
                    "y": 821.9495991484416
                }
            ]
        },
        {
            "id": "QhOTb7K6_",
            "type": "RECTANGLE",
            "tags": [
                "Scissors"
            ],
            "boundingBox": {
                "height": 51.27603310708651,
                "width": 107.04088992454506,
                "left": 1269.3150798934755,
                "top": 737.2326507688729
            },
            "points": [
                {
                    "x": 1269.3150798934755,
                    "y": 737.2326507688729
                },
                {
                    "x": 1376.3559698180204,
                    "y": 737.2326507688729
                },
                {
                    "x": 1376.3559698180204,
                    "y": 788.5086838759594
                },
                {
                    "x": 1269.3150798934755,
                    "y": 788.5086838759594
                }
            ]
        },
        {
            "id": "d1ypjBkvN",
            "type": "RECTANGLE",
            "tags": [
                "Syringe"
            ],
            "boundingBox": {
                "height": 84.71694837956876,
                "width": 44.600393919218824,
                "left": 1308.340407234798,
                "top": 607.9278384701942
            },
            "points": [
                {
                    "x": 1308.340407234798,
                    "y": 607.9278384701942
                },
                {
                    "x": 1352.940801154017,
                    "y": 607.9278384701942
                },
                {
                    "x": 1352.940801154017,
                    "y": 692.6447868497629
                },
                {
                    "x": 1308.340407234798,
                    "y": 692.6447868497629
                }
            ]
        },
        {
            "id": "z8GvlDl-0",
            "type": "RECTANGLE",
            "tags": [
                "Hand"
            ],
            "boundingBox": {
                "height": 71.34061000361557,
                "width": 138.26106857523303,
                "left": 1165.6193131380383,
                "top": 548.8489066441687
            },
            "points": [
                {
                    "x": 1165.6193131380383,
                    "y": 548.8489066441687
                },
                {
                    "x": 1303.8803817132712,
                    "y": 548.8489066441687
                },
                {
                    "x": 1303.8803817132712,
                    "y": 620.1895166477842
                },
                {
                    "x": 1165.6193131380383,
                    "y": 620.1895166477842
                }
            ]
        },
        {
            "id": "Tgxv5Y26s",
            "type": "RECTANGLE",
            "tags": [
                "Hand"
            ],
            "boundingBox": {
                "height": 75.79938946226663,
                "width": 108.15579227696405,
                "left": 1215.7947736351532,
                "top": 635.795244753063
            },
            "points": [
                {
                    "x": 1215.7947736351532,
                    "y": 635.795244753063
                },
                {
                    "x": 1323.9505659121173,
                    "y": 635.795244753063
                },
                {
                    "x": 1323.9505659121173,
                    "y": 711.5946342153296
                },
                {
                    "x": 1215.7947736351532,
                    "y": 711.5946342153296
                }
            ]
        }
    ],
    "version": "2.1.0"
}