{
    "asset": {
        "format": "jpg",
        "id": "6edcbf46e03dcc2659535596b8bb1d18",
        "name": "DoNothing_3_2.jpg",
        "path": "file:D:/Dataset/All%20data/DoNothing_3_2.jpg",
        "size": {
            "width": 1920,
            "height": 1080
        },
        "state": 2,
        "type": 1
    },
    "regions": [
        {
            "id": "_6iad25gI",
            "type": "RECTANGLE",
            "tags": [
                "Scissors"
            ],
            "boundingBox": {
                "height": 66.49210869511472,
                "width": 120.35698398576514,
                "left": 1178.224967332073,
                "top": 731.2449761885631
            },
            "points": [
                {
                    "x": 1178.224967332073,
                    "y": 731.2449761885631
                },
                {
                    "x": 1298.5819513178383,
                    "y": 731.2449761885631
                },
                {
                    "x": 1298.5819513178383,
                    "y": 797.7370848836779
                },
                {
                    "x": 1178.224967332073,
                    "y": 797.7370848836779
                }
            ]
        },
        {
            "id": "4e8JepThQX",
            "type": "RECTANGLE",
            "tags": [
                "Scissors"
            ],
            "boundingBox": {
                "height": 72.72947480406943,
                "width": 120.35698398576514,
                "left": 1260.8581412644573,
                "top": 820.2531645569621
            },
            "points": [
                {
                    "x": 1260.8581412644573,
                    "y": 820.2531645569621
                },
                {
                    "x": 1381.2151252502226,
                    "y": 820.2531645569621
                },
                {
                    "x": 1381.2151252502226,
                    "y": 892.9826393610315
                },
                {
                    "x": 1260.8581412644573,
                    "y": 892.9826393610315
                }
            ]
        },
        {
            "id": "JslKXJh1uT",
            "type": "RECTANGLE",
            "tags": [
                "Scissors"
            ],
            "boundingBox": {
                "height": 35.94170292721519,
                "width": 109.57879225978648,
                "left": 1359.6587417982653,
                "top": 652.1732436554341
            },
            "points": [
                {
                    "x": 1359.6587417982653,
                    "y": 652.1732436554341
                },
                {
                    "x": 1469.2375340580518,
                    "y": 652.1732436554341
                },
                {
                    "x": 1469.2375340580518,
                    "y": 688.1149465826494
                },
                {
                    "x": 1359.6587417982653,
                    "y": 688.1149465826494
                }
            ]
        },
        {
            "id": "BJZBiSiLr",
            "type": "RECTANGLE",
            "tags": [
                "Scissors"
            ],
            "boundingBox": {
                "height": 66.95633651426174,
                "width": 116.37468533668975,
                "left": 1415.092358598175,
                "top": 801.5208435058594
            },
            "points": [
                {
                    "x": 1415.092358598175,
                    "y": 801.5208435058594
                },
                {
                    "x": 1531.4670439348647,
                    "y": 801.5208435058594
                },
                {
                    "x": 1531.4670439348647,
                    "y": 868.4771800201211
                },
                {
                    "x": 1415.092358598175,
                    "y": 868.4771800201211
                }
            ]
        },
        {
            "id": "lxHk0Cuw5L",
            "type": "RECTANGLE",
            "tags": [
                "Scissors"
            ],
            "boundingBox": {
                "height": 43.90579121224832,
                "width": 127.35358322844557,
                "left": 1401.9177991268093,
                "top": 725.7833094244835
            },
            "points": [
                {
                    "x": 1401.9177991268093,
                    "y": 725.7833094244835
                },
                {
                    "x": 1529.271382355255,
                    "y": 725.7833094244835
                },
                {
                    "x": 1529.271382355255,
                    "y": 769.6891006367318
                },
                {
                    "x": 1401.9177991268093,
                    "y": 769.6891006367318
                }
            ]
        },
        {
            "id": "BVb7hc6YKs",
            "type": "RECTANGLE",
            "tags": [
                "Scissors"
            ],
            "boundingBox": {
                "height": 63.66338742659396,
                "width": 69.16614222781624,
                "left": 1297.6196949732537,
                "top": 654.4364232824952
            },
            "points": [
                {
                    "x": 1297.6196949732537,
                    "y": 654.4364232824952
                },
                {
                    "x": 1366.7858372010699,
                    "y": 654.4364232824952
                },
                {
                    "x": 1366.7858372010699,
                    "y": 718.0998107090892
                },
                {
                    "x": 1297.6196949732537,
                    "y": 718.0998107090892
                }
            ]
        },
        {
            "id": "_WywF4fCYc",
            "type": "RECTANGLE",
            "tags": [
                "Scissors"
            ],
            "boundingBox": {
                "height": 47.198691144085565,
                "width": 97.71092275015734,
                "left": 1202.1045321349907,
                "top": 667.6081704773359
            },
            "points": [
                {
                    "x": 1202.1045321349907,
                    "y": 667.6081704773359
                },
                {
                    "x": 1299.815454885148,
                    "y": 667.6081704773359
                },
                {
                    "x": 1299.815454885148,
                    "y": 714.8068616214214
                },
                {
                    "x": 1202.1045321349907,
                    "y": 714.8068616214214
                }
            ]
        },
        {
            "id": "dNwTEJnzU8",
            "type": "RECTANGLE",
            "tags": [
                "Syringe"
            ],
            "boundingBox": {
                "height": 18.65999567428691,
                "width": 90.02576305852737,
                "left": 1161.4831704295154,
                "top": 648.9481748030489
            },
            "points": [
                {
                    "x": 1161.4831704295154,
                    "y": 648.9481748030489
                },
                {
                    "x": 1251.5089334880429,
                    "y": 648.9481748030489
                },
                {
                    "x": 1251.5089334880429,
                    "y": 667.6081704773359
                },
                {
                    "x": 1161.4831704295154,
                    "y": 667.6081704773359
                }
            ]
        },
        {
            "id": "h0EqDYbJOO",
            "type": "RECTANGLE",
            "tags": [
                "Scissors"
            ],
            "boundingBox": {
                "height": 27.441094929739933,
                "width": 103.20022419760856,
                "left": 1186.7343110840152,
                "top": 630.2882282845926
            },
            "points": [
                {
                    "x": 1186.7343110840152,
                    "y": 630.2882282845926
                },
                {
                    "x": 1289.9345352816238,
                    "y": 630.2882282845926
                },
                {
                    "x": 1289.9345352816238,
                    "y": 657.7293232143325
                },
                {
                    "x": 1186.7343110840152,
                    "y": 657.7293232143325
                }
            ]
        },
        {
            "id": "F7ir49MlWP",
            "type": "RECTANGLE",
            "tags": [
                "Scissors"
            ],
            "boundingBox": {
                "height": 26.343494389681208,
                "width": 99.90658432976716,
                "left": 1147.2108293344872,
                "top": 624.7999798051462
            },
            "points": [
                {
                    "x": 1147.2108293344872,
                    "y": 624.7999798051462
                },
                {
                    "x": 1247.1174136642544,
                    "y": 624.7999798051462
                },
                {
                    "x": 1247.1174136642544,
                    "y": 651.1434741948275
                },
                {
                    "x": 1147.2108293344872,
                    "y": 651.1434741948275
                }
            ]
        },
        {
            "id": "IfsYgbnHRu",
            "type": "RECTANGLE",
            "tags": [
                "Tweezers"
            ],
            "boundingBox": {
                "height": 18.659946518456376,
                "width": 61.48108086847074,
                "left": 1137.329909730963,
                "top": 595.1635854836278
            },
            "points": [
                {
                    "x": 1137.329909730963,
                    "y": 595.1635854836278
                },
                {
                    "x": 1198.8109905994336,
                    "y": 595.1635854836278
                },
                {
                    "x": 1198.8109905994336,
                    "y": 613.8235320020842
                },
                {
                    "x": 1137.329909730963,
                    "y": 613.8235320020842
                }
            ]
        },
        {
            "id": "drjKIrdXyY",
            "type": "RECTANGLE",
            "tags": [
                "Syringe"
            ],
            "boundingBox": {
                "height": 32.92934340918624,
                "width": 74.65554200755192,
                "left": 1186.7343110840152,
                "top": 602.8470841990221
            },
            "points": [
                {
                    "x": 1186.7343110840152,
                    "y": 602.8470841990221
                },
                {
                    "x": 1261.3898530915671,
                    "y": 602.8470841990221
                },
                {
                    "x": 1261.3898530915671,
                    "y": 635.7764276082083
                },
                {
                    "x": 1186.7343110840152,
                    "y": 635.7764276082083
                }
            ]
        },
        {
            "id": "lB-Lvi1G43",
            "type": "RECTANGLE",
            "tags": [
                "Scissors"
            ],
            "boundingBox": {
                "height": 47.1987402999161,
                "width": 102.10234424166143,
                "left": 1345.9262163703588,
                "top": 680.7798685163459
            },
            "points": [
                {
                    "x": 1345.9262163703588,
                    "y": 680.7798685163459
                },
                {
                    "x": 1448.02856061202,
                    "y": 680.7798685163459
                },
                {
                    "x": 1448.02856061202,
                    "y": 727.9786088162621
                },
                {
                    "x": 1345.9262163703588,
                    "y": 727.9786088162621
                }
            ]
        }
    ],
    "version": "2.1.0"
}