{
    "asset": {
        "format": "jpg",
        "id": "7a23816edef581eecacccdc99702c154",
        "name": "ReturnScissor_35_9.jpg",
        "path": "file:D:/Dataset/All%20data/ReturnScissor_35_9.jpg",
        "size": {
            "width": 1920,
            "height": 1080
        },
        "state": 2,
        "type": 1
    },
    "regions": [
        {
            "id": "z4kFLU_U52",
            "type": "RECTANGLE",
            "tags": [
                "Scissors"
            ],
            "boundingBox": {
                "height": 46.81725364843545,
                "width": 101.46568464269863,
                "left": 1176.7694462938305,
                "top": 644.7128036703651
            },
            "points": [
                {
                    "x": 1176.7694462938305,
                    "y": 644.7128036703651
                },
                {
                    "x": 1278.2351309365292,
                    "y": 644.7128036703651
                },
                {
                    "x": 1278.2351309365292,
                    "y": 691.5300573188006
                },
                {
                    "x": 1176.7694462938305,
                    "y": 691.5300573188006
                }
            ]
        },
        {
            "id": "eEwHfnvyLl",
            "type": "RECTANGLE",
            "tags": [
                "Syringe"
            ],
            "boundingBox": {
                "height": 39.01435492949645,
                "width": 163.90618064802487,
                "left": 1238.0949012427875,
                "top": 736.1179905705097
            },
            "points": [
                {
                    "x": 1238.0949012427875,
                    "y": 736.1179905705097
                },
                {
                    "x": 1402.0010818908122,
                    "y": 736.1179905705097
                },
                {
                    "x": 1402.0010818908122,
                    "y": 775.1323455000062
                },
                {
                    "x": 1238.0949012427875,
                    "y": 775.1323455000062
                }
            ]
        },
        {
            "id": "iVninxfsmA",
            "type": "RECTANGLE",
            "tags": [
                "Syringe"
            ],
            "boundingBox": {
                "height": 28.98213581383119,
                "width": 99.23574123391035,
                "left": 1378.5859132268088,
                "top": 711.5946342153296
            },
            "points": [
                {
                    "x": 1378.5859132268088,
                    "y": 711.5946342153296
                },
                {
                    "x": 1477.8216544607192,
                    "y": 711.5946342153296
                },
                {
                    "x": 1477.8216544607192,
                    "y": 740.5767700291608
                },
                {
                    "x": 1378.5859132268088,
                    "y": 740.5767700291608
                }
            ]
        },
        {
            "id": "1LdjPbwwEl",
            "type": "RECTANGLE",
            "tags": [
                "Syringe"
            ],
            "boundingBox": {
                "height": 80.2581689209177,
                "width": 97.00565912117177,
                "left": 1419.84132268087,
                "top": 669.2361600255452
            },
            "points": [
                {
                    "x": 1419.84132268087,
                    "y": 669.2361600255452
                },
                {
                    "x": 1516.8469818020417,
                    "y": 669.2361600255452
                },
                {
                    "x": 1516.8469818020417,
                    "y": 749.4943289464629
                },
                {
                    "x": 1419.84132268087,
                    "y": 749.4943289464629
                }
            ]
        },
        {
            "id": "rXnHILeJJ-",
            "type": "RECTANGLE",
            "tags": [
                "Syringe"
            ],
            "boundingBox": {
                "height": 54.620152367374445,
                "width": 109.27083333333334,
                "left": 1369.665862183755,
                "top": 814.1467697621019
            },
            "points": [
                {
                    "x": 1369.665862183755,
                    "y": 814.1467697621019
                },
                {
                    "x": 1478.9366955170883,
                    "y": 814.1467697621019
                },
                {
                    "x": 1478.9366955170883,
                    "y": 868.7669221294764
                },
                {
                    "x": 1369.665862183755,
                    "y": 868.7669221294764
                }
            ]
        },
        {
            "id": "OxgPbP0QLZ",
            "type": "RECTANGLE",
            "tags": [
                "Tweezers"
            ],
            "boundingBox": {
                "height": 21.179306427491454,
                "width": 71.36054704837994,
                "left": 1359.630770084332,
                "top": 636.9099049514261
            },
            "points": [
                {
                    "x": 1359.630770084332,
                    "y": 636.9099049514261
                },
                {
                    "x": 1430.991317132712,
                    "y": 636.9099049514261
                },
                {
                    "x": 1430.991317132712,
                    "y": 658.0892113789175
                },
                {
                    "x": 1359.630770084332,
                    "y": 658.0892113789175
                }
            ]
        },
        {
            "id": "dSvgIQ99Eq",
            "type": "RECTANGLE",
            "tags": [
                "Scissors"
            ],
            "boundingBox": {
                "height": 44.587863919109914,
                "width": 143.83599644917888,
                "left": 1239.2099422991566,
                "top": 774.017685301643
            },
            "points": [
                {
                    "x": 1239.2099422991566,
                    "y": 774.017685301643
                },
                {
                    "x": 1383.0459387483356,
                    "y": 774.017685301643
                },
                {
                    "x": 1383.0459387483356,
                    "y": 818.605549220753
                },
                {
                    "x": 1239.2099422991566,
                    "y": 818.605549220753
                }
            ]
        },
        {
            "id": "PxWWmMnKOe",
            "type": "RECTANGLE",
            "tags": [
                "Scissors"
            ],
            "boundingBox": {
                "height": 30.09679601219432,
                "width": 86.97056702174878,
                "left": 1205.7596815357301,
                "top": 700.447685568702
            },
            "points": [
                {
                    "x": 1205.7596815357301,
                    "y": 700.447685568702
                },
                {
                    "x": 1292.730248557479,
                    "y": 700.447685568702
                },
                {
                    "x": 1292.730248557479,
                    "y": 730.5444815808963
                },
                {
                    "x": 1205.7596815357301,
                    "y": 730.5444815808963
                }
            ]
        },
        {
            "id": "l6oEbjFLYf",
            "type": "RECTANGLE",
            "tags": [
                "Tweezers"
            ],
            "boundingBox": {
                "height": 20.064576896529058,
                "width": 66.90052152685308,
                "left": 1257.050044385264,
                "top": 604.5837192099062
            },
            "points": [
                {
                    "x": 1257.050044385264,
                    "y": 604.5837192099062
                },
                {
                    "x": 1323.9505659121173,
                    "y": 604.5837192099062
                },
                {
                    "x": 1323.9505659121173,
                    "y": 624.6482961064353
                },
                {
                    "x": 1257.050044385264,
                    "y": 624.6482961064353
                }
            ]
        },
        {
            "id": "FLo6Uc9b3",
            "type": "RECTANGLE",
            "tags": [
                "Scissors"
            ],
            "boundingBox": {
                "height": 64.65244081563897,
                "width": 102.58072569906791,
                "left": 1248.1299933422104,
                "top": 802.999751782875
            },
            "points": [
                {
                    "x": 1248.1299933422104,
                    "y": 802.999751782875
                },
                {
                    "x": 1350.7107190412783,
                    "y": 802.999751782875
                },
                {
                    "x": 1350.7107190412783,
                    "y": 867.6521925985139
                },
                {
                    "x": 1248.1299933422104,
                    "y": 867.6521925985139
                }
            ]
        },
        {
            "id": "MVGm00V8P",
            "type": "RECTANGLE",
            "tags": [
                "Hand"
            ],
            "boundingBox": {
                "height": 65.76717034660138,
                "width": 122.65090989791389,
                "left": 1000.5980914336441,
                "top": 674.8095996825595
            },
            "points": [
                {
                    "x": 1000.5980914336441,
                    "y": 674.8095996825595
                },
                {
                    "x": 1123.249001331558,
                    "y": 674.8095996825595
                },
                {
                    "x": 1123.249001331558,
                    "y": 740.5767700291608
                },
                {
                    "x": 1000.5980914336441,
                    "y": 740.5767700291608
                }
            ]
        },
        {
            "id": "QwRjZHPhj",
            "type": "RECTANGLE",
            "tags": [
                "Hand"
            ],
            "boundingBox": {
                "height": 110.35503426571128,
                "width": 91.43073124722592,
                "left": 1175.654405237461,
                "top": 566.6840244787729
            },
            "points": [
                {
                    "x": 1175.654405237461,
                    "y": 566.6840244787729
                },
                {
                    "x": 1267.0851364846872,
                    "y": 566.6840244787729
                },
                {
                    "x": 1267.0851364846872,
                    "y": 677.0390587444842
                },
                {
                    "x": 1175.654405237461,
                    "y": 677.0390587444842
                }
            ]
        }
    ],
    "version": "2.1.0"
}