{
    "asset": {
        "format": "jpg",
        "id": "d6dbf45fe0a76c70651fee0873dd710b",
        "name": "TakeSyringe_9_2.jpg",
        "path": "file:D:/Dataset/All%20data/TakeSyringe_9_2.jpg",
        "size": {
            "width": 1920,
            "height": 1080
        },
        "state": 2,
        "type": 1
    },
    "regions": [
        {
            "id": "zuU_7fJLH",
            "type": "RECTANGLE",
            "tags": [
                "Scissors"
            ],
            "boundingBox": {
                "height": 25.638016553543256,
                "width": 111.50077674212162,
                "left": 1206.8747225920995,
                "top": 593.4367705632786
            },
            "points": [
                {
                    "x": 1206.8747225920995,
                    "y": 593.4367705632786
                },
                {
                    "x": 1318.375499334221,
                    "y": 593.4367705632786
                },
                {
                    "x": 1318.375499334221,
                    "y": 619.0747871168219
                },
                {
                    "x": 1206.8747225920995,
                    "y": 619.0747871168219
                }
            ]
        },
        {
            "id": "SPj_069qWA",
            "type": "RECTANGLE",
            "tags": [
                "Tweezers"
            ],
            "boundingBox": {
                "height": 16.720457636241125,
                "width": 62.44049600532623,
                "left": 1213.5646915224147,
                "top": 617.9600575858594
            },
            "points": [
                {
                    "x": 1213.5646915224147,
                    "y": 617.9600575858594
                },
                {
                    "x": 1276.0051875277409,
                    "y": 617.9600575858594
                },
                {
                    "x": 1276.0051875277409,
                    "y": 634.6805152221006
                },
                {
                    "x": 1213.5646915224147,
                    "y": 634.6805152221006
                }
            ]
        },
        {
            "id": "Id2RvzZlBR",
            "type": "RECTANGLE",
            "tags": [
                "Tweezers"
            ],
            "boundingBox": {
                "height": 23.408626824217723,
                "width": 127.11093541944075,
                "left": 1214.6797325787838,
                "top": 629.1070755650863
            },
            "points": [
                {
                    "x": 1214.6797325787838,
                    "y": 629.1070755650863
                },
                {
                    "x": 1341.7906679982245,
                    "y": 629.1070755650863
                },
                {
                    "x": 1341.7906679982245,
                    "y": 652.5157023893041
                },
                {
                    "x": 1214.6797325787838,
                    "y": 652.5157023893041
                }
            ]
        },
        {
            "id": "nkNWW3V13x",
            "type": "RECTANGLE",
            "tags": [
                "Scissors"
            ],
            "boundingBox": {
                "height": 33.44091527248225,
                "width": 93.6608133599645,
                "left": 1226.944768086995,
                "top": 654.7450921186296
            },
            "points": [
                {
                    "x": 1226.944768086995,
                    "y": 654.7450921186296
                },
                {
                    "x": 1320.6055814469596,
                    "y": 654.7450921186296
                },
                {
                    "x": 1320.6055814469596,
                    "y": 688.1860073911118
                },
                {
                    "x": 1226.944768086995,
                    "y": 688.1860073911118
                }
            ]
        },
        {
            "id": "6SzFcKNXLh",
            "type": "RECTANGLE",
            "tags": [
                "Scissors"
            ],
            "boundingBox": {
                "height": 40.12908446045885,
                "width": 91.43073124722592,
                "left": 1236.9798601864181,
                "top": 698.2182958393764
            },
            "points": [
                {
                    "x": 1236.9798601864181,
                    "y": 698.2182958393764
                },
                {
                    "x": 1328.4105914336442,
                    "y": 698.2182958393764
                },
                {
                    "x": 1328.4105914336442,
                    "y": 738.3473802998353
                },
                {
                    "x": 1236.9798601864181,
                    "y": 738.3473802998353
                }
            ]
        },
        {
            "id": "ZoBbFHYNjf",
            "type": "RECTANGLE",
            "tags": [
                "Scissors"
            ],
            "boundingBox": {
                "height": 33.44091527248225,
                "width": 121.53586884154461,
                "left": 1239.2099422991566,
                "top": 749.4943289464629
            },
            "points": [
                {
                    "x": 1239.2099422991566,
                    "y": 749.4943289464629
                },
                {
                    "x": 1360.7458111407013,
                    "y": 749.4943289464629
                },
                {
                    "x": 1360.7458111407013,
                    "y": 782.9352442189452
                },
                {
                    "x": 1239.2099422991566,
                    "y": 782.9352442189452
                }
            ]
        },
        {
            "id": "JAYwO4L1Cz",
            "type": "RECTANGLE",
            "tags": [
                "Scissors"
            ],
            "boundingBox": {
                "height": 47.93198317939785,
                "width": 134.91608411007547,
                "left": 1247.0149522858412,
                "top": 789.6234134069218
            },
            "points": [
                {
                    "x": 1247.0149522858412,
                    "y": 789.6234134069218
                },
                {
                    "x": 1381.9310363959166,
                    "y": 789.6234134069218
                },
                {
                    "x": 1381.9310363959166,
                    "y": 837.5553965863196
                },
                {
                    "x": 1247.0149522858412,
                    "y": 837.5553965863196
                }
            ]
        },
        {
            "id": "6F0ysGqe5X",
            "type": "RECTANGLE",
            "tags": [
                "Syringe"
            ],
            "boundingBox": {
                "height": 55.734881898336845,
                "width": 190.66647248113628,
                "left": 1361.8608521970707,
                "top": 821.9495991484416
            },
            "points": [
                {
                    "x": 1361.8608521970707,
                    "y": 821.9495991484416
                },
                {
                    "x": 1552.527324678207,
                    "y": 821.9495991484416
                },
                {
                    "x": 1552.527324678207,
                    "y": 877.6844810467785
                },
                {
                    "x": 1361.8608521970707,
                    "y": 877.6844810467785
                }
            ]
        },
        {
            "id": "VAnTUIdBQj",
            "type": "RECTANGLE",
            "tags": [
                "Scissors"
            ],
            "boundingBox": {
                "height": 36.78503453277018,
                "width": 160.5611961828673,
                "left": 1483.3967210386152,
                "top": 878.7991412451416
            },
            "points": [
                {
                    "x": 1483.3967210386152,
                    "y": 878.7991412451416
                },
                {
                    "x": 1643.9579172214826,
                    "y": 878.7991412451416
                },
                {
                    "x": 1643.9579172214826,
                    "y": 915.5841757779118
                },
                {
                    "x": 1483.3967210386152,
                    "y": 915.5841757779118
                }
            ]
        },
        {
            "id": "dVy5thjMJ9",
            "type": "RECTANGLE",
            "tags": [
                "Syringe"
            ],
            "boundingBox": {
                "height": 81.37282911928084,
                "width": 92.54577230359521,
                "left": 1477.8216544607192,
                "top": 747.2649392171375
            },
            "points": [
                {
                    "x": 1477.8216544607192,
                    "y": 747.2649392171375
                },
                {
                    "x": 1570.3674267643144,
                    "y": 747.2649392171375
                },
                {
                    "x": 1570.3674267643144,
                    "y": 828.6377683364183
                },
                {
                    "x": 1477.8216544607192,
                    "y": 828.6377683364183
                }
            ]
        },
        {
            "id": "diyxMM69o7",
            "type": "RECTANGLE",
            "tags": [
                "Syringe"
            ],
            "boundingBox": {
                "height": 72.4552702019787,
                "width": 60.21041389258766,
                "left": 1494.5468541944076,
                "top": 677.0390587444842
            },
            "points": [
                {
                    "x": 1494.5468541944076,
                    "y": 677.0390587444842
                },
                {
                    "x": 1554.7572680869953,
                    "y": 677.0390587444842
                },
                {
                    "x": 1554.7572680869953,
                    "y": 749.4943289464629
                },
                {
                    "x": 1494.5468541944076,
                    "y": 749.4943289464629
                }
            ]
        },
        {
            "id": "ResjzraN9e",
            "type": "RECTANGLE",
            "tags": [
                "Syringe"
            ],
            "boundingBox": {
                "height": 33.44091527248225,
                "width": 115.96094096759876,
                "left": 1355.170744562805,
                "top": 707.1358547566786
            },
            "points": [
                {
                    "x": 1355.170744562805,
                    "y": 707.1358547566786
                },
                {
                    "x": 1471.131685530404,
                    "y": 707.1358547566786
                },
                {
                    "x": 1471.131685530404,
                    "y": 740.5767700291608
                },
                {
                    "x": 1355.170744562805,
                    "y": 740.5767700291608
                }
            ]
        },
        {
            "id": "LVenKb-G9U",
            "type": "RECTANGLE",
            "tags": [
                "Scissors"
            ],
            "boundingBox": {
                "height": 35.67030500180778,
                "width": 65.7854804704838,
                "left": 1409.806230581447,
                "top": 760.6412775930906
            },
            "points": [
                {
                    "x": 1409.806230581447,
                    "y": 760.6412775930906
                },
                {
                    "x": 1475.5917110519308,
                    "y": 760.6412775930906
                },
                {
                    "x": 1475.5917110519308,
                    "y": 796.3115825948984
                },
                {
                    "x": 1409.806230581447,
                    "y": 796.3115825948984
                }
            ]
        },
        {
            "id": "gi-0aeuERl",
            "type": "RECTANGLE",
            "tags": [
                "Scissors"
            ],
            "boundingBox": {
                "height": 28.982066481231925,
                "width": 73.59049045716823,
                "left": 1414.2662561029738,
                "top": 790.7381429378842
            },
            "points": [
                {
                    "x": 1414.2662561029738,
                    "y": 790.7381429378842
                },
                {
                    "x": 1487.856746560142,
                    "y": 790.7381429378842
                },
                {
                    "x": 1487.856746560142,
                    "y": 819.7202094191161
                },
                {
                    "x": 1414.2662561029738,
                    "y": 819.7202094191161
                }
            ]
        },
        {
            "id": "bGAioCRPvV",
            "type": "RECTANGLE",
            "tags": [
                "Tweezers"
            ],
            "boundingBox": {
                "height": 20.064576896529058,
                "width": 70.24550599201065,
                "left": 1426.5312916111852,
                "top": 655.8597523169927
            },
            "points": [
                {
                    "x": 1426.5312916111852,
                    "y": 655.8597523169927
                },
                {
                    "x": 1496.7767976031957,
                    "y": 655.8597523169927
                },
                {
                    "x": 1496.7767976031957,
                    "y": 675.9243292135218
                },
                {
                    "x": 1426.5312916111852,
                    "y": 675.9243292135218
                }
            ]
        },
        {
            "id": "sGb3oBW_I8",
            "type": "RECTANGLE",
            "tags": [
                "Tweezers"
            ],
            "boundingBox": {
                "height": 14.490998574316329,
                "width": 72.47558810474922,
                "left": 1425.4162505548159,
                "top": 639.1393640133509
            },
            "points": [
                {
                    "x": 1425.4162505548159,
                    "y": 639.1393640133509
                },
                {
                    "x": 1497.891838659565,
                    "y": 639.1393640133509
                },
                {
                    "x": 1497.891838659565,
                    "y": 653.6303625876673
                },
                {
                    "x": 1425.4162505548159,
                    "y": 653.6303625876673
                }
            ]
        },
        {
            "id": "khbQoft8B7W",
            "type": "RECTANGLE",
            "tags": [
                "Scissors"
            ],
            "boundingBox": {
                "height": 55.73481256573758,
                "width": 43.48535286284954,
                "left": 1333.9856580115402,
                "top": 610.1572281995197
            },
            "points": [
                {
                    "x": 1333.9856580115402,
                    "y": 610.1572281995197
                },
                {
                    "x": 1377.4710108743898,
                    "y": 610.1572281995197
                },
                {
                    "x": 1377.4710108743898,
                    "y": 665.8920407652573
                },
                {
                    "x": 1333.9856580115402,
                    "y": 665.8920407652573
                }
            ]
        },
        {
            "id": "TowaKGZ4Uzf",
            "type": "RECTANGLE",
            "tags": [
                "Scissors"
            ],
            "boundingBox": {
                "height": 45.702593450072314,
                "width": 43.48535286284954,
                "left": 1333.9856580115402,
                "top": 592.3220410323162
            },
            "points": [
                {
                    "x": 1333.9856580115402,
                    "y": 592.3220410323162
                },
                {
                    "x": 1377.4710108743898,
                    "y": 592.3220410323162
                },
                {
                    "x": 1377.4710108743898,
                    "y": 638.0246344823885
                },
                {
                    "x": 1333.9856580115402,
                    "y": 638.0246344823885
                }
            ]
        },
        {
            "id": "104XQRJXR",
            "type": "RECTANGLE",
            "tags": [
                "Scissors"
            ],
            "boundingBox": {
                "height": 34.55564480344465,
                "width": 98.12083888149135,
                "left": 1444.3713936972927,
                "top": 680.3831086721729
            },
            "points": [
                {
                    "x": 1444.3713936972927,
                    "y": 680.3831086721729
                },
                {
                    "x": 1542.4922325787838,
                    "y": 680.3831086721729
                },
                {
                    "x": 1542.4922325787838,
                    "y": 714.9387534756175
                },
                {
                    "x": 1444.3713936972927,
                    "y": 714.9387534756175
                }
            ]
        },
        {
            "id": "iyag_r8z_",
            "type": "RECTANGLE",
            "tags": [
                "Hand"
            ],
            "boundingBox": {
                "height": 61.30832155535104,
                "width": 142.72109409675988,
                "left": 1083.1087716378163,
                "top": 592.3220410323162
            },
            "points": [
                {
                    "x": 1083.1087716378163,
                    "y": 592.3220410323162
                },
                {
                    "x": 1225.829865734576,
                    "y": 592.3220410323162
                },
                {
                    "x": 1225.829865734576,
                    "y": 653.6303625876673
                },
                {
                    "x": 1083.1087716378163,
                    "y": 653.6303625876673
                }
            ]
        }
    ],
    "version": "2.1.0"
}