{
    "asset": {
        "format": "jpg",
        "id": "dc1f96517c7d47e27a147c4c546c4b72",
        "name": "TakeScissor_20_7.jpg",
        "path": "file:D:/Dataset/All%20data/TakeScissor_20_7.jpg",
        "size": {
            "width": 1920,
            "height": 1080
        },
        "state": 2,
        "type": 1
    },
    "regions": [
        {
            "id": "ExR5e-q7J",
            "type": "RECTANGLE",
            "tags": [
                "Scissors"
            ],
            "boundingBox": {
                "height": 36.15129442157019,
                "width": 119.79670910563254,
                "left": 1072.1131779174914,
                "top": 790.4919755653257
            },
            "points": [
                {
                    "x": 1072.1131779174914,
                    "y": 790.4919755653257
                },
                {
                    "x": 1191.909887023124,
                    "y": 790.4919755653257
                },
                {
                    "x": 1191.909887023124,
                    "y": 826.6432699868959
                },
                {
                    "x": 1072.1131779174914,
                    "y": 826.6432699868959
                }
            ]
        },
        {
            "id": "B8kREJeFeh",
            "type": "RECTANGLE",
            "tags": [
                "Scissors"
            ],
            "boundingBox": {
                "height": 38.41076086304765,
                "width": 114.14589706676264,
                "left": 1075.5036651408134,
                "top": 758.8596140267103
            },
            "points": [
                {
                    "x": 1075.5036651408134,
                    "y": 758.8596140267103
                },
                {
                    "x": 1189.649562207576,
                    "y": 758.8596140267103
                },
                {
                    "x": 1189.649562207576,
                    "y": 797.270374889758
                },
                {
                    "x": 1075.5036651408134,
                    "y": 797.270374889758
                }
            ]
        },
        {
            "id": "8GMUZ1p9fg",
            "type": "RECTANGLE",
            "tags": [
                "Scissors"
            ],
            "boundingBox": {
                "height": 49.70809307043492,
                "width": 87.02216798632355,
                "left": 1090.195692088807,
                "top": 730.6163678292768
            },
            "points": [
                {
                    "x": 1090.195692088807,
                    "y": 730.6163678292768
                },
                {
                    "x": 1177.2178600751304,
                    "y": 730.6163678292768
                },
                {
                    "x": 1177.2178600751304,
                    "y": 780.3244608997117
                },
                {
                    "x": 1090.195692088807,
                    "y": 780.3244608997117
                }
            ]
        },
        {
            "id": "OZj7U1gREV",
            "type": "RECTANGLE",
            "tags": [
                "Scissors"
            ],
            "boundingBox": {
                "height": 32.762094759354014,
                "width": 74.5902971477416,
                "left": 1239.3765394434947,
                "top": 740.7839668159253
            },
            "points": [
                {
                    "x": 1239.3765394434947,
                    "y": 740.7839668159253
                },
                {
                    "x": 1313.9668365912362,
                    "y": 740.7839668159253
                },
                {
                    "x": 1313.9668365912362,
                    "y": 773.5460615752793
                },
                {
                    "x": 1239.3765394434947,
                    "y": 773.5460615752793
                }
            ]
        },
        {
            "id": "-z7Xrg07F0",
            "type": "RECTANGLE",
            "tags": [
                "Scissors"
            ],
            "boundingBox": {
                "height": 36.15129442157019,
                "width": 71.19989427748786,
                "left": 1250.6780791681663,
                "top": 765.6380133511427
            },
            "points": [
                {
                    "x": 1250.6780791681663,
                    "y": 765.6380133511427
                },
                {
                    "x": 1321.877973445654,
                    "y": 765.6380133511427
                },
                {
                    "x": 1321.877973445654,
                    "y": 801.789307772713
                },
                {
                    "x": 1250.6780791681663,
                    "y": 801.789307772713
                }
            ]
        },
        {
            "id": "3yKip7hvzm",
            "type": "RECTANGLE",
            "tags": [
                "Scissors"
            ],
            "boundingBox": {
                "height": 22.594537933222735,
                "width": 108.49516938096095,
                "left": 1054.030663746176,
                "top": 639.1084407151297
            },
            "points": [
                {
                    "x": 1054.030663746176,
                    "y": 639.1084407151297
                },
                {
                    "x": 1162.525833127137,
                    "y": 639.1084407151297
                },
                {
                    "x": 1162.525833127137,
                    "y": 661.7029786483525
                },
                {
                    "x": 1054.030663746176,
                    "y": 661.7029786483525
                }
            ]
        },
        {
            "id": "A522b7okaI",
            "type": "RECTANGLE",
            "tags": [
                "Tweezers"
            ],
            "boundingBox": {
                "height": 46.31885124770147,
                "width": 25.99365102573331,
                "left": 1156.875021088267,
                "top": 597.3084801898659
            },
            "points": [
                {
                    "x": 1156.875021088267,
                    "y": 597.3084801898659
                },
                {
                    "x": 1182.8686721140004,
                    "y": 597.3084801898659
                },
                {
                    "x": 1182.8686721140004,
                    "y": 643.6273314375675
                },
                {
                    "x": 1156.875021088267,
                    "y": 643.6273314375675
                }
            ]
        },
        {
            "id": "zcqS8GDDa",
            "type": "RECTANGLE",
            "tags": [
                "Hand"
            ],
            "boundingBox": {
                "height": 100.54579288005677,
                "width": 131.09824883030413,
                "left": 1199.8210238775418,
                "top": 598.4382134106047
            },
            "points": [
                {
                    "x": 1199.8210238775418,
                    "y": 598.4382134106047
                },
                {
                    "x": 1330.919272707846,
                    "y": 598.4382134106047
                },
                {
                    "x": 1330.919272707846,
                    "y": 698.9840062906615
                },
                {
                    "x": 1199.8210238775418,
                    "y": 698.9840062906615
                }
            ]
        },
        {
            "id": "oaNky-VRv",
            "type": "RECTANGLE",
            "tags": [
                "Hand"
            ],
            "boundingBox": {
                "height": 97.15663537835785,
                "width": 157.09189985603743,
                "left": 1021.2561226268671,
                "top": 645.8867978790449
            },
            "points": [
                {
                    "x": 1021.2561226268671,
                    "y": 645.8867978790449
                },
                {
                    "x": 1178.3480224829045,
                    "y": 645.8867978790449
                },
                {
                    "x": 1178.3480224829045,
                    "y": 743.0434332574027
                },
                {
                    "x": 1021.2561226268671,
                    "y": 743.0434332574027
                }
            ]
        }
    ],
    "version": "2.1.0"
}